investimentos/__init__.py
investimentos/investimentos.py
prj_investiment-0.1.1.dist-info/LICENSE
prj_investiment-0.1.1.dist-info/METADATA
prj_investiment-0.1.1.dist-info/WHEEL
prj_investiment-0.1.1.dist-info/top_level.txt
prj_investiment-0.1.1.dist-info/RECORD
